example_package_rsmahmud/__init__.py
example_package_rsmahmud/example.py
example_package_rsmahmud-0.0.3.dist-info/licenses/LICENSE
example_package_rsmahmud-0.0.3.dist-info/METADATA
example_package_rsmahmud-0.0.3.dist-info/WHEEL
example_package_rsmahmud-0.0.3.dist-info/top_level.txt
example_package_rsmahmud-0.0.3.dist-info/RECORD
