Metadata-Version: 2.4
Name: example_package_rsmahmud
Version: 0.0.3
Summary: A small example package
Author-email: Hasan Rasel <rrss.mahmud@gmail.com>
License-Expression: MIT
Project-URL: Homepage, https://github.com/rsmahmud/packaging_example
Project-URL: Issues, https://github.com/rsmahmud/packaging_example/issues
Classifier: Programming Language :: Python :: 3
Classifier: Operating System :: OS Independent
Requires-Python: >=3.9
License-File: LICENSE
Dynamic: license-file
